alu.v
module alu(
           input wire [15:0] a,
           input wire [15:0] b,
           input wire [3:0] op,
           output reg [15:0] result,
           output wire zero_flag // this is for the bne beq ops when you compare two shits and see if the diff is zero or not zero
           );
   assign zero_flag = (result == 16'b0) ? 1'b1 : 1'b0;
   always @(*) begin
      case (op)
        4'b0000: result = a+b;
        4'b0001: result = a-b;
        4'b0010: result = a*b;
        4'b0011: result = ~(a&b);
        4'b0100: result = ~(a|b);
        default: result = 16'b0;
      endcase // case (op)
   end
endmodule

benchtest.v
module alu_tb;
    reg  [15:0] a;
    reg  [15:0] b;
    reg  [3:0]  op;
    wire [15:0] result;
    wire zero_flag;
    alu dut (
        .a(a),
        .b(b),
        .op(op),
        .result(result),
         .zero_flag(zero_flag)
    );

    initial begin
        $dumpfile("alu.vcd");
        $dumpvars(0, alu_tb);

        // ── ADD tests ──
        op = 4'b0000;
        a = 16'd10;   b = 16'd5;    #10;
        $display("ADD  %0d + %0d = %0d  (expect 15)",  a, b, result);

        a = 16'd1000; b = 16'd2000; #10;
        $display("ADD  %0d + %0d = %0d  (expect 3000)", a, b, result);

        a = 16'd65535; b = 16'd1;   #10;
        $display("ADD  overflow: %0d + %0d = %0d  (expect 0 wraparound)", a, b, result); // here zero_flag set to one?

        // ── SUB tests ──
        op = 4'b0001;
        a = 16'd20;  b = 16'd8;    #10;
        $display("SUB  %0d - %0d = %0d  (expect 12)",  a, b, result);

        a = 16'd5;   b = 16'd10;   #10;
        $display("SUB  %0d - %0d = %0d  (expect 65531 underflow)", a, b, result);

        a = 16'd100; b = 16'd100;  #10;
        $display("SUB  %0d - %0d = %0d  (expect 0)",   a, b, result); // also check if the zero_flag is set to 1 maybe?

       // mul
       op = 4'b0010;
       a = 16'd2;
       b = 16'd19;
       #10;
       $display("MUL %0d*%0d = %0d (2*19)", a, b, result);

       a = 16'd0;
       b = 16'd0;
       #10;
       $display("MUL %0d*%0d = %0d (0*0)", a, b, result); // check for zero_flag here too

       op = 4'b0011;
       a = 16'd10;
       b = 16'd11;
       #10;
       $display("NAND %0d, %0d = %0d", a,b,result);



        // ── default case ──
        op = 4'b1111;
        a = 16'd999; b = 16'd999;  #10;
        $display("DEF  op=1111 result = %0d  (expect 0)", result);

        $finish;
    end

endmodule

alu.vcd
$date
	Fri Jun  5 11:35:22 2026
$end
$version
	Icarus Verilog
$end
$timescale
	1s
$end
$scope module alu_tb $end
$var wire 1 ! zero_flag $end
$var wire 16 " result [15:0] $end
$var reg 16 # a [15:0] $end
$var reg 16 $ b [15:0] $end
$var reg 4 % op [3:0] $end
$scope module dut $end
$var wire 16 & a [15:0] $end
$var wire 16 ' b [15:0] $end
$var wire 4 ( op [3:0] $end
$var wire 1 ! zero_flag $end
$var reg 16 ) result [15:0] $end
$upscope $end
$upscope $end
$enddefinitions $end
$comment Show the parameter values. $end
$dumpall
$end
#0
$dumpvars
b1111 )
b0 (
b101 '
b1010 &
b0 %
b101 $
b1010 #
b1111 "
0!
$end
#10
b101110111000 "
b101110111000 )
b11111010000 $
b11111010000 '
b1111101000 #
b1111101000 &
#20
1!
b0 "
b0 )
b1 $
b1 '
b1111111111111111 #
b1111111111111111 &
#30
0!
b1100 "
b1100 )
b1000 $
b1000 '
b10100 #
b10100 &
b1 %
b1 (
#40
b1111111111111011 "
b1111111111111011 )
b1010 $
b1010 '
b101 #
b101 &
#50
1!
b0 "
b0 )
b1100100 $
b1100100 '
b1100100 #
b1100100 &
#60
0!
b100110 "
b100110 )
b10011 $
b10011 '
b10 #
b10 &
b10 %
b10 (
#70
1!
b0 "
b0 )
b0 $
b0 '
b0 #
b0 &
#80
0!
b1111111111110101 "
b1111111111110101 )
b1011 $
b1011 '
b1010 #
b1010 &
b11 %
b11 (
#90
1!
b0 "
b0 )
b1111100111 $
b1111100111 '
b1111100111 #
b1111100111 &
b1111 %
b1111 (
