dmem.v
module dmem(
            input wire         clk,
            input wire         write_enable,
            input wire [15:0]  addr,
            input wire [15:0]  write_data,
            output wire [15:0] read_data
            );

   reg [15:0] mem [0:255];
   assign read_data = mem[addr];

   always @(posedge clk) begin
      if (write_enable)
        mem[addr] <= write_data;
   end
endmodule // dmem

alu.v
module alu(
           input wire [15:0] a,
           input wire [15:0] b,
           input wire [3:0] op,
           output reg [15:0] result,
           output wire zero_flag // this is for the bne beq ops when you compare two shits and see if the diff is zero or not zero
           );
   assign zero_flag = (result == 16'b0) ? 1'b1 : 1'b0;
   always @(*) begin
      case (op)
        4'b0000: result = a+b;
        4'b0001: result = a-b;
        4'b0010: result = a*b;
        4'b0011: result = ~(a&b);
        4'b0100: result = ~(a|b);
        default: result = 16'b0;
      endcase // case (op)
   end
endmodule

reg_file.v
module regfile(
               input wire       clk,
               input wire       write_enable,
               input wire [2:0] rs1,
               input wire [2:0] rs2,
               input wire [2:0] rd,
               input wire [15:0] write_data,
               output wire [15:0] read1, // this is reading from rs1
               output wire [15:0] read2 // this is for reading from rs2
               );
   reg [15:0] registers [0:7];
   integer    i;
   initial begin
      for (i = 0; i < 8; i = i + 1)
        registers[i] = 16'b0;
   end
   assign read1 = (rs1 == 3'b000) ? 16'b0 : registers[rs1]; // if rs1 == 0th register then save 0 on it
   assign read2 = (rs2 == 3'b000) ? 16'b0 : registers[rs2];

   always @(posedge clk) begin
      if (write_enable && rd != 3'b000) // which enables write only for all registers - rs0
        registers[rd] <= write_data;
   end
endmodule // regfile

instruction_memory.v
module imem(
            input wire [15:0]  addr,
            output wire [15:0] instruction
            );
   reg [15:0] mem [0:255];
   initial begin
      // mem[0] = 16'hAAAA;
      // mem[1] = 16'hBBBB;
      // mem[2] = 16'hCCCC;
      // mem[3] = 16'hDDDD;
      // mem[0] = 16'hC20A;
      // mem[1] = 16'hC414;
      // mem[2] = 16'h0650;
      // mem[3] = 16'hB000;
      // mem[4] = 16'hB000;
      // mem[5] = 16'hB000;
      $readmemh("out.hex",mem);
   end
   assign instruction = mem[addr];

endmodule // imen

cpu.v
/*
ADD   0000    reg_write=1, alu_op=ADD
SUB   0001    reg_write=1, alu_op=SUB
MUL   0010    reg_write=1, alu_op=MUL
NAND  0011    reg_write=1, alu_op=NAND
NOR   0100    reg_write=1, alu_op=NOR
MOV   0101    reg_write=1, alu_op=passthrough
LDI   1100    reg_write=1, alu_src=immediate
LOAD  0110    reg_write=1, mem_read=1
STORE 0111    mem_write=1
JMP   1000    branch=1
BEQ   1001    branch=1, alu_op=SUB (compare by subtracting)
BNE   1010    branch=1, alu_op=SUB
HALT  1011    halt=1
*/
module cpu(
           input wire clk,
           input wire reset
           );
   reg [15:0] pc; // 16 bit program counter

   // assigning the bit wise fields for the opcodes registers etc
   wire [15:0] instruction;
   wire [3:0]  opcode = instruction[15:12];
   wire [2:0]  rd = instruction[11:9];
   wire [2:0]  rs1 = instruction[8:6];
   wire [2:0]  rs2 = instruction[5:3];
   wire [7:0]  imm8    = instruction[7:0];   // for LDI load immediate load the constant value present in the instruction to the register
   wire [11:0] addrj  = instruction[11:0];  // for JMP
   wire [5:0]  offset6 = instruction[5:0];   // for BEQ/BNE
   wire [2:0] branch_rs1 = instruction[11:9];
   wire [2:0] branch_rs2 = instruction[8:6];

   // main control signals
   reg         reg_write;
   reg         mem_read;
   reg         mem_write;
   reg         alu_src;
   reg         is_branch;
   reg         is_halt;
   reg [3:0]   alu_op;

   // wires connecting to the modules
   wire [15:0] read1, read2;
   wire [15:0] alu_result;
   wire        zero_flag;
   wire [15:0] mem_read_data;


   wire [15:0] alu_b = alu_src ? {8'b0, imm8} : read2;
   wire [15:0] write_data = mem_read ? mem_read_data : alu_result;
   wire [2:0] alu_rs1 = is_branch ? branch_rs1 : rs1;
   wire [2:0] alu_rs2 = is_branch ? branch_rs2 : rs2;
   // then importing those shitty ahh things that i wrote for gods sake this is gonna be a pain

   imem imem0(
              .addr(pc),
              .instruction(instruction)
              );
   regfile rf0(
               .clk(clk),
               .write_enable(reg_write),
               .rs1(alu_rs1),      // use muxed version
               .rs2(alu_rs2),      // use muxed version
               .rd(rd),
               .write_data(write_data),
               .read1(read1),
               .read2(read2)
               );
   alu alu0(
            .a(read1),
            .b(alu_b),
            .op(alu_op),
            .result(alu_result),
            .zero_flag(zero_flag)
            );
   dmem dmem0(
              .clk(clk),
              .write_enable(mem_write),
              .addr(alu_result),
              .write_data(read2),
              .read_data(mem_read_data)
              );

   always @(*) begin
      // make sure that all of the signals are set to default values aka 0
      reg_write = 0;
      mem_read = 0;
      mem_write = 0;
      alu_src   = 0;
      is_branch = 0;
      is_halt   = 0;
      alu_op    = 4'b0000;

      case (opcode)
        4'b0000: begin reg_write=1; alu_op=4'b0000; end  // ADD
        4'b0001: begin reg_write=1; alu_op=4'b0001; end  // SUB
        4'b0010: begin reg_write=1; alu_op=4'b0010; end  // MUL
        4'b0011: begin reg_write=1; alu_op=4'b0011; end  // NAND
        4'b0100: begin reg_write=1; alu_op=4'b0100; end  // NOR
        4'b0101: begin reg_write=1; alu_op=4'b0000; end  // MOV (rs2=R0 so result=rs1)
        4'b1100: begin reg_write=1; alu_src=1;      end  // LDI
        4'b0110: begin reg_write=1; mem_read=1;     end  // LOAD
        4'b0111: begin mem_write=1;                 end  // STORE
        4'b1000: begin is_branch=1;                 end  // JMP
        4'b1001: begin is_branch=1; alu_op=4'b0001; end  // BEQ
        4'b1010: begin is_branch=1; alu_op=4'b0001; end  // BNE
        4'b1011: begin is_halt=1;                   end  // HALT
      endcase // case (opcode)
   end // always @ (*)

   always @(posedge clk) begin
      if (reset) begin
         pc <= 16'b0;
      end else if (is_halt) begin
         pc <= pc; // this would apparently freeze the cpu cool shit
      end else if (opcode == 4'b1000) begin // this is a JMP instruction
         pc <= {4'b0, addrj};
      end else if (opcode == 4'b1001) begin // this is a BEQ instruction
         pc <= pc + {{10{offset6[5]}}, offset6};
      end else if (opcode == 4'b1010 && !zero_flag) begin // this is a BNE instruction
         pc <= pc + {{10{offset6[5]}}, offset6};
      end else begin
         pc <= pc+1;
      end
   end // always @ (posedge clk)
endmodule // cpu

cpu_tb.v
module cpu_tb;
   reg clk;
   reg reset;

   cpu dut(
           .clk(clk),
           .reset(reset)
           );
   initial clk = 0;
   always #5 clk = ~clk;

   initial begin
      $dumpfile("cpu.vcd");
      $dumpvars(0, cpu_tb);

      reset = 1;
      @(posedge clk);
      #1;
      @(posedge clk);
      #1;
      reset = 0;
      repeat(10) begin
         @(posedge clk); #1;
         $display("PC=%0d | IF=%h | R1=%0d R2=%0d R3=%0d R4=%0d R5=%0d",
                  dut.pc,
                  dut.instruction,
                  dut.rf0.registers[1],
                  dut.rf0.registers[2],
                  dut.rf0.registers[3],
                  dut.rf0.registers[4],
                  dut.rf0.registers[5]
                  );
         // $display("PC=%0d | instr=%h | R1=%0d R2=%0d R3=%0d | zero=%b",
         //          dut.pc,
         //          dut.instruction,
         //          dut.rf0.registers[1],
         //          dut.rf0.registers[2],
         //          dut.rf0.registers[3],
         //          dut.zero_flag
         //          );
      end

      $finish;
   end // initial begin

endmodule // cpu_tb

cpu.vcd
$date
	Sun Jun  7 11:05:44 2026
$end
$version
	Icarus Verilog
$end
$timescale
	1s
$end
$scope module cpu_tb $end
$var reg 1 ! clk $end
$var reg 1 " reset $end
$scope module dut $end
$var wire 1 ! clk $end
$var wire 1 " reset $end
$var wire 1 # zero_flag $end
$var wire 16 $ write_data [15:0] $end
$var wire 3 % rs2 [2:0] $end
$var wire 3 & rs1 [2:0] $end
$var wire 16 ' read2 [15:0] $end
$var wire 16 ( read1 [15:0] $end
$var wire 3 ) rd [2:0] $end
$var wire 4 * opcode [3:0] $end
$var wire 6 + offset6 [5:0] $end
$var wire 16 , mem_read_data [15:0] $end
$var wire 16 - instruction [15:0] $end
$var wire 8 . imm8 [7:0] $end
$var wire 3 / branch_rs2 [2:0] $end
$var wire 3 0 branch_rs1 [2:0] $end
$var wire 3 1 alu_rs2 [2:0] $end
$var wire 3 2 alu_rs1 [2:0] $end
$var wire 16 3 alu_result [15:0] $end
$var wire 16 4 alu_b [15:0] $end
$var wire 12 5 addrj [11:0] $end
$var reg 4 6 alu_op [3:0] $end
$var reg 1 7 alu_src $end
$var reg 1 8 is_branch $end
$var reg 1 9 is_halt $end
$var reg 1 : mem_read $end
$var reg 1 ; mem_write $end
$var reg 16 < pc [15:0] $end
$var reg 1 = reg_write $end
$scope module alu0 $end
$var wire 16 > b [15:0] $end
$var wire 4 ? op [3:0] $end
$var wire 1 # zero_flag $end
$var wire 16 @ a [15:0] $end
$var reg 16 A result [15:0] $end
$upscope $end
$scope module dmem0 $end
$var wire 16 B addr [15:0] $end
$var wire 1 ! clk $end
$var wire 16 C read_data [15:0] $end
$var wire 1 ; write_enable $end
$var wire 16 D write_data [15:0] $end
$upscope $end
$scope module imem0 $end
$var wire 16 E addr [15:0] $end
$var wire 16 F instruction [15:0] $end
$upscope $end
$scope module rf0 $end
$var wire 1 ! clk $end
$var wire 3 G rd [2:0] $end
$var wire 3 H rs1 [2:0] $end
$var wire 3 I rs2 [2:0] $end
$var wire 16 J write_data [15:0] $end
$var wire 1 = write_enable $end
$var wire 16 K read2 [15:0] $end
$var wire 16 L read1 [15:0] $end
$var integer 32 M i [31:0] $end
$upscope $end
$upscope $end
$upscope $end
$enddefinitions $end
$comment Show the parameter values. $end
$dumpall
$end
#0
$dumpvars
b1000 M
bx L
bx K
bx J
bx I
bx H
bx G
bx F
bx E
bx D
bx C
bx B
bx A
bx @
bx ?
bx >
x=
bx <
x;
x:
x9
x8
x7
bx 6
bx 5
bx 4
bx 3
bx 2
bx 1
bx 0
bx /
bx .
bx -
bx ,
bx +
bx *
bx )
bx (
bx '
bx &
bx %
bx $
x#
1"
0!
$end
#5
0#
b11 $
b11 J
b11 3
b11 A
b11 B
b0 '
b0 D
b0 K
b0 (
b0 @
b0 L
b11 4
b11 >
b0 1
b0 I
b0 2
b0 H
b0 6
b0 ?
09
08
17
0;
0:
1=
b0 /
b1 0
b11 +
b1000000011 5
b11 .
b0 %
b0 &
b1 )
b1 G
b1100 *
b1100001000000011 -
b1100001000000011 F
b0 <
b0 E
1!
#10
0!
#15
1!
#16
0"
#20
0!
#25
b1 $
b1 J
b1 3
b1 A
b1 B
b1 4
b1 >
b10 0
b1 +
b10000000001 5
b1 .
b10 )
b10 G
b1100010000000001 -
b1100010000000001 F
b1 <
b1 E
1!
#30
0!
#35
0#
b10 $
b10 J
b1 '
b1 D
b1 K
b11 (
b11 @
b11 L
b10 3
b10 A
b10 B
b1 4
b1 >
b10 1
b10 I
b1 2
b1 H
b1 6
b1 ?
07
1=
b1 /
b1 0
b10000 +
b1001010000 5
b1010000 .
b10 %
b1 &
b1 )
b1 G
b1 *
b1001001010000 -
b1001001010000 F
b10 <
b10 E
1!
#40
0!
#45
b0 4
b0 >
b0 '
b0 D
b0 K
b10 $
b10 J
b10 3
b10 A
b10 B
b11 1
b11 I
18
b1 6
b1 ?
0=
b10 (
b10 @
b10 L
b11 /
b111111 +
b1011111111 5
b11111111 .
b111 %
b11 &
b1010 *
b1010001011111111 -
b1010001011111111 F
b11 <
b11 E
1!
#50
0!
#55
b1 $
b1 J
b1 3
b1 A
b1 B
b1 4
b1 >
b1 '
b1 D
b1 K
b10 1
b10 I
1=
b1 6
b1 ?
08
b1 /
b10000 +
b1001010000 5
b1010000 .
b10 %
b1 &
b1 *
b1001001010000 -
b1001001010000 F
b10 <
b10 E
1!
#60
0!
#65
b0 4
b0 >
b0 '
b0 D
b0 K
0#
b1 $
b1 J
b1 3
b1 A
b1 B
b11 1
b11 I
18
b1 6
b1 ?
0=
b1 (
b1 @
b1 L
b11 /
b111111 +
b1011111111 5
b11111111 .
b111 %
b11 &
b1010 *
b1010001011111111 -
b1010001011111111 F
b11 <
b11 E
1!
#70
0!
#75
1#
b0 $
b0 J
b0 3
b0 A
b0 B
b1 4
b1 >
b1 '
b1 D
b1 K
b10 1
b10 I
1=
b1 6
b1 ?
08
b1 /
b10000 +
b1001010000 5
b1010000 .
b10 %
b1 &
b1 *
b1001001010000 -
b1001001010000 F
b10 <
b10 E
1!
#80
0!
#85
b0 4
b0 >
b0 '
b0 D
b0 K
1#
b0 $
b0 J
b0 3
b0 A
b0 B
b11 1
b11 I
18
b1 6
b1 ?
0=
b0 (
b0 @
b0 L
b11 /
b111111 +
b1011111111 5
b11111111 .
b111 %
b11 &
b1010 *
b1010001011111111 -
b1010001011111111 F
b11 <
b11 E
1!
#90
0!
#95
b0 1
b0 I
b0 2
b0 H
19
b0 6
b0 ?
08
b0 /
b0 0
b0 +
b0 5
b0 .
b0 %
b0 &
b0 )
b0 G
b1011 *
b1011000000000000 -
b1011000000000000 F
b100 <
b100 E
1!
